perfect_pixel/__init__.py
perfect_pixel/perfect_pixel.py
perfect_pixel/perfect_pixel_noCV2.py
perfect_pixel-0.1.4.dist-info/METADATA
perfect_pixel-0.1.4.dist-info/WHEEL
perfect_pixel-0.1.4.dist-info/top_level.txt
perfect_pixel-0.1.4.dist-info/RECORD
