Metadata-Version: 2.4
Name: perfect-pixel
Version: 0.1.4
Summary: A library for auto grid detection and pixel art refinement.
Author-email: theAmusing <amusingyyy@gmail.com>
License: MIT
Project-URL: Homepage, https://github.com/theamusing/perfectPixel
Project-URL: Web Demo, https://github.com/theamusing/perfectPixel_webdemo
Keywords: pixel,pixel-art,pixel-style,computer-vision,opencv,numpy,image-processing
Classifier: Programming Language :: Python :: 3
Classifier: License :: OSI Approved :: MIT License
Classifier: Operating System :: OS Independent
Classifier: Topic :: Scientific/Engineering :: Image Processing
Requires-Python: >=3.8
Requires-Dist: numpy>=1.20.0
Provides-Extra: opencv
Requires-Dist: opencv-python; extra == "opencv"
